UART/SIPO/sipo.v
module sipo(
    input reset,
    input baud_clk,
    input data_tx,
    output reg [10:0]frame,
    output reg active_flag,
    output reg done_flag
);

parameter idle = 0, active=1;
reg state;
reg [3:0] clock_count;
always @(posedge baud_clk or reset) begin
  if(reset) begin
    state <= idle;
    active_flag <= 0;
    done_flag <= 0;
    clock_count <= 0;
  end
  else begin
    case (state) 
    idle : begin
      active_flag <= 0;

      if(data_tx == 0) begin
        state <= active;
        active_flag <= 1;
      end
    end

    active: begin
      frame[clock_count] <= data_tx;
      if(clock_count == 10) begin
        clock_count <= 0;
        state <= idle;
        done_flag <= 1;
        active_flag <= 0;
      end
      else begin
        clock_count <= clock_count + 1;
      end
    end
    default : state <= idle;
    endcase
  end
end
endmodule

UART/SIPO/tb.v
module tb();

  reg reset;
  reg baud_clk, data_tx;
  wire [10:0] frame;
  wire active_flag;
  wire done_flag;

  sipo uut(
    .reset(reset), 
    .baud_clk(baud_clk),
    .data_tx(data_tx),
    .frame(frame),
    .active_flag(active_flag),
    .done_flag(done_flag)
  );

  // Baud clock: 10 time units period
  always #5 baud_clk = ~baud_clk;

  initial begin
    $dumpfile("test.vcd");
    $dumpvars(0, tb);
    baud_clk = 0;
    data_tx = 1; // idle line
    reset = 1;
    #10 reset = 0;

    data_tx = 1;
  #10 data_tx = 1;
  #10 data_tx = 0;
  #10 data_tx = 1;
  #10 data_tx = 1;
  #10 data_tx = 1;
  #10 data_tx = 0;
  #10 data_tx = 1;
  #10 data_tx = 1;
 #10 data_tx = 0;
  #10 data_tx = 0;
  #10 data_tx = 1;
  #10 data_tx = 1;
  #10 data_tx = 1;
    #100;

    $display("\n==== Decoded Frame ====");
    $display("Full frame : %b", frame);
    $display("Start bit  : %b", frame[0]);
    $display("Data       : %b", frame[8:1]);
    $display("Parity bit : %b", frame[9]);
    $display("Stop bit   : %b", frame[10]);
    $display("Data (hex) : %h", frame[8:1]);
    $display("========================\n");

    $finish;
  end

endmodule

UART/SIPO/test.vcd
$date
	Wed Jul 16 19:27:58 2025
$end
$version
	Icarus Verilog
$end
$timescale
	1s
$end
$scope module tb $end
$var wire 11 ! frame [10:0] $end
$var wire 1 " done_flag $end
$var wire 1 # active_flag $end
$var reg 1 $ baud_clk $end
$var reg 1 % data_tx $end
$var reg 1 & reset $end
$scope module uut $end
$var wire 1 $ baud_clk $end
$var wire 1 % data_tx $end
$var wire 1 & reset $end
$var reg 1 # active_flag $end
$var reg 4 ' clock_count [3:0] $end
$var reg 1 " done_flag $end
$var reg 11 ( frame [10:0] $end
$var reg 1 ) state $end
$upscope $end
$upscope $end
$enddefinitions $end
#0
$dumpvars
0)
bx (
b0 '
1&
1%
0$
0#
0"
bx !
$end
#5
1$
#10
0$
0&
#15
1$
#20
0$
#25
1$
#30
0$
0%
#35
1#
1)
1$
#40
0$
1%
#45
b1 '
bx1 !
bx1 (
1$
#50
0$
#55
b10 '
bx11 !
bx11 (
1$
#60
0$
#65
b11 '
bx111 !
bx111 (
1$
#70
0$
0%
#75
b100 '
bx0111 !
bx0111 (
1$
#80
0$
1%
#85
b101 '
bx10111 !
bx10111 (
1$
#90
0$
#95
b110 '
bx110111 !
bx110111 (
1$
#100
0$
0%
#105
b111 '
bx0110111 !
bx0110111 (
1$
#110
0$
#115
b1000 '
bx00110111 !
bx00110111 (
1$
#120
0$
1%
#125
b1001 '
bx100110111 !
bx100110111 (
1$
#130
0$
#135
b1010 '
bx1100110111 !
bx1100110111 (
1$
#140
0$
#145
0#
1"
0)
b0 '
b11100110111 !
b11100110111 (
1$
