UART/TX/piso.v
module piso(
    input reset,
    input baud_clk,
    input [7:0] data_in,
    input send, //enable to start send
    input parity_bit,

    output reg data_tx,
    output reg active_flag,
    output reg done_flag
);

reg [3:0] clock_count;
reg [10:0] frame; //
reg state;

parameter idle = 0;
parameter active = 1;


always @(posedge baud_clk or posedge reset) begin
  if(reset) begin
    state <= idle;
    clock_count <= 0;
    data_tx <= 1'b1;
    active_flag <= 0;
    done_flag <= 0;
    frame <= {11{1'b1}};
  end
  else begin
    case (state)
        idle: begin
          data_tx <= 1'b1;
          clock_count <= 0;
          active_flag <= 0;
          done_flag <= 0;
        
          if(send) begin
            state <= active;
            active_flag <= 1'b1;
            frame <= {1'b1,parity_bit,data_in,1'b0};
          end
        end 

        active: begin
            data_tx <= frame[0];
          if(clock_count == 10) begin
            state <= idle;
            clock_count <= 0;
            done_flag <= 1;
            active_flag <= 0;
          end
          else begin
            frame <= frame >> 1;
            clock_count <= clock_count + 1;
            active_flag <= 1;
            done_flag <= 0;
          end
        end 
        default: state <= idle;
    endcase
  end

end









endmodule

UART/PISO/tb.v
`timescale 1ns/1ps
module tb();

reg baud_clk, reset;
reg [7:0] data_in;
reg send, parity_bit;

wire data_tx, active_flag, done_flag;


piso uut(.baud_clk(baud_clk),
         .reset(reset),
         .data_in(data_in),
         .send(send),
         .parity_bit(parity_bit),
         .data_tx(data_tx),
         .active_flag(active_flag),
         .done_flag(done_flag));

always #5 baud_clk = ~baud_clk;

initial begin
  $dumpfile("test.vcd");
  $dumpvars(0, tb);

  $monitor("data send,%b bit received %b", data_in, data_tx);
end

// Stimulus
initial begin
  // Init signals
  parity_bit = 0;
  baud_clk = 0;
  reset = 1;
  send = 0;
  data_in = 8'b0;

  #20 reset = 0;

  // Wait a few cycles, then send
  #20;
  data_in = 8'b01001010;
  send = 1;
  #10;        // one clk cycle
  send = 0;

  // Wait until done_flag is high
  wait (done_flag);
  #20;        // brief pause

  data_in = 8'b01001010;
  send = 1;
  #10;
  send = 0;
  wait (done_flag);
  #20;

  data_in = 8'b01001010;
  send = 1;
  #10;
  send = 0;
  wait (done_flag);
  #20;

  data_in = 8'b01011010;
  send = 1;
  #10;
  send = 0;
  wait (done_flag);
  #20;

  $finish;
end

endmodule

UART/PISO/test.vcd
$date
	Tue Jul 15 20:46:02 2025
$end
$version
	Icarus Verilog
$end
$timescale
	1ps
$end
$scope module tb $end
$var wire 1 ! done_flag $end
$var wire 1 " data_tx $end
$var wire 1 # active_flag $end
$var reg 1 $ baud_clk $end
$var reg 8 % data_in [7:0] $end
$var reg 1 & parity_bit $end
$var reg 1 ' reset $end
$var reg 1 ( send $end
$scope module uut $end
$var wire 1 $ baud_clk $end
$var wire 8 ) data_in [7:0] $end
$var wire 1 & parity_bit $end
$var wire 1 ' reset $end
$var wire 1 ( send $end
$var reg 1 # active_flag $end
$var reg 4 * clock_count [3:0] $end
$var reg 1 " data_tx $end
$var reg 1 ! done_flag $end
$var reg 11 + frame [10:0] $end
$var reg 1 , state $end
$upscope $end
$upscope $end
$enddefinitions $end
#0
$dumpvars
0,
b11111111111 +
b0 *
b0 )
0(
1'
0&
b0 %
0$
0#
1"
0!
$end
#5000
1$
#10000
0$
#15000
1$
#20000
0$
0'
#25000
1$
#30000
0$
#35000
1$
#40000
0$
1(
b1001010 %
b1001010 )
#45000
b10010010100 +
1#
1,
1$
#50000
0$
0(
#55000
b1 *
b1001001010 +
0"
1$
#60000
0$
#65000
b10 *
b100100101 +
1$
#70000
0$
#75000
b11 *
b10010010 +
1"
1$
#80000
0$
#85000
b100 *
b1001001 +
0"
1$
#90000
0$
#95000
b101 *
b100100 +
1"
1$
#100000
0$
#105000
b110 *
b10010 +
0"
1$
#110000
0$
#115000
b111 *
b1001 +
1$
#120000
0$
#125000
b1000 *
b100 +
1"
1$
#130000
0$
#135000
b1001 *
b10 +
0"
1$
#140000
0$
#145000
b1010 *
b1 +
1$
#150000
0$
#155000
0#
1!
b0 *
0,
1"
1$
#160000
0$
#165000
0!
1$
#170000
0$
#175000
b10010010100 +
1#
1,
1$
1(
#180000
0$
#185000
b1 *
b1001001010 +
0"
1$
0(
#190000
0$
#195000
b10 *
b100100101 +
1$
#200000
0$
#205000
b11 *
b10010010 +
1"
1$
#210000
0$
#215000
b100 *
b1001001 +
0"
1$
#220000
0$
#225000
b101 *
b100100 +
1"
1$
#230000
0$
#235000
b110 *
b10010 +
0"
1$
#240000
0$
#245000
b111 *
b1001 +
1$
#250000
0$
#255000
b1000 *
b100 +
1"
1$
#260000
0$
#265000
b1001 *
b10 +
0"
1$
#270000
0$
#275000
b1010 *
b1 +
1$
#280000
0$
#285000
0#
1!
b0 *
0,
1"
1$
#290000
0$
#295000
0!
1$
#300000
0$
#305000
b10010010100 +
1#
1,
1$
1(
#310000
0$
#315000
b1 *
b1001001010 +
0"
1$
0(
#320000
0$
#325000
b10 *
b100100101 +
1$
#330000
0$
#335000
b11 *
b10010010 +
1"
1$
#340000
0$
#345000
b100 *
b1001001 +
0"
1$
#350000
0$
#355000
b101 *
b100100 +
1"
1$
#360000
0$
#365000
b110 *
b10010 +
0"
1$
#370000
0$
#375000
b111 *
b1001 +
1$
#380000
0$
#385000
b1000 *
b100 +
1"
1$
#390000
0$
#395000
b1001 *
b10 +
0"
1$
#400000
0$
#405000
b1010 *
b1 +
1$
#410000
0$
#415000
0#
1!
b0 *
0,
1"
1$
#420000
0$
#425000
0!
1$
#430000
0$
#435000
b10010110100 +
1#
1,
1$
1(
b1011010 %
b1011010 )
#440000
0$
#445000
b1 *
b1001011010 +
0"
1$
0(
#450000
0$
#455000
b10 *
b100101101 +
1$
#460000
0$
#465000
b11 *
b10010110 +
1"
1$
#470000
0$
#475000
b100 *
b1001011 +
0"
1$
#480000
0$
#485000
b101 *
b100101 +
1"
1$
#490000
0$
#495000
b110 *
b10010 +
1$
#500000
0$
#505000
b111 *
b1001 +
0"
1$
#510000
0$
#515000
b1000 *
b100 +
1"
1$
#520000
0$
#525000
b1001 *
b10 +
0"
1$
#530000
0$
#535000
b1010 *
b1 +
1$
#540000
0$
#545000
0#
1!
b0 *
0,
1"
1$
#550000
0$
#555000
0!
1$
